{
    "asreviewVersion": "1.2",
    "apiVersion": "1.1.2",
    "data": {
        "items": [
            {
                "id": "recall",
                "title": "Recall",
                "value": [
                    [
                        0.1,
                        0.6744186046511628
                    ],
                    [
                        0.25,
                        0.9069767441860465
                    ],
                    [
                        0.5,
                        0.9767441860465116
                    ],
                    [
                        0.75,
                        1.0
                    ],
                    [
                        0.9,
                        1.0
                    ]
                ]
            },
            {
                "id": "wss",
                "title": "Work Saved over Sampling",
                "value": [
                    [
                        0.95,
                        0.5659666128163705
                    ]
                ]
            },
            {
                "id": "erf",
                "title": "Extra Relevant record Found",
                "value": [
                    [
                        0.1,
                        0.5697674418604651
                    ]
                ]
            },
            {
                "id": "atd",
                "title": "Average time to discovery",
                "value": 192.0
            },
            {
                "id": "td",
                "title": "Time to discovery",
                "value": [
                    [
                        93,
                        3
                    ],
                    [
                        998,
                        4
                    ],
                    [
                        130,
                        5
                    ],
                    [
                        228,
                        7
                    ],
                    [
                        123,
                        8
                    ],
                    [
                        992,
                        14
                    ],
                    [
                        83,
                        15
                    ],
                    [
                        129,
                        16
                    ],
                    [
                        1534,
                        22
                    ],
                    [
                        95,
                        23
                    ],
                    [
                        500,
                        25
                    ],
                    [
                        437,
                        29
                    ],
                    [
                        59,
                        31
                    ],
                    [
                        473,
                        32
                    ],
                    [
                        60,
                        35
                    ],
                    [
                        113,
                        36
                    ],
                    [
                        110,
                        37
                    ],
                    [
                        741,
                        39
                    ],
                    [
                        1658,
                        44
                    ],
                    [
                        421,
                        45
                    ],
                    [
                        204,
                        50
                    ],
                    [
                        338,
                        52
                    ],
                    [
                        55,
                        55
                    ],
                    [
                        145,
                        58
                    ],
                    [
                        567,
                        59
                    ],
                    [
                        120,
                        62
                    ],
                    [
                        116,
                        64
                    ],
                    [
                        17,
                        65
                    ],
                    [
                        127,
                        68
                    ],
                    [
                        984,
                        73
                    ],
                    [
                        563,
                        74
                    ],
                    [
                        994,
                        79
                    ],
                    [
                        111,
                        82
                    ],
                    [
                        158,
                        84
                    ],
                    [
                        85,
                        85
                    ],
                    [
                        829,
                        90
                    ],
                    [
                        346,
                        93
                    ],
                    [
                        1673,
                        94
                    ],
                    [
                        69,
                        98
                    ],
                    [
                        1829,
                        99
                    ],
                    [
                        97,
                        102
                    ],
                    [
                        1032,
                        107
                    ],
                    [
                        1043,
                        109
                    ],
                    [
                        449,
                        116
                    ],
                    [
                        134,
                        117
                    ],
                    [
                        575,
                        118
                    ],
                    [
                        1739,
                        122
                    ],
                    [
                        161,
                        125
                    ],
                    [
                        1037,
                        142
                    ],
                    [
                        1579,
                        144
                    ],
                    [
                        1688,
                        145
                    ],
                    [
                        496,
                        148
                    ],
                    [
                        584,
                        150
                    ],
                    [
                        629,
                        163
                    ],
                    [
                        126,
                        171
                    ],
                    [
                        968,
                        178
                    ],
                    [
                        314,
                        183
                    ],
                    [
                        409,
                        185
                    ],
                    [
                        779,
                        188
                    ],
                    [
                        1663,
                        192
                    ],
                    [
                        1507,
                        201
                    ],
                    [
                        772,
                        209
                    ],
                    [
                        1112,
                        221
                    ],
                    [
                        1753,
                        224
                    ],
                    [
                        760,
                        238
                    ],
                    [
                        878,
                        252
                    ],
                    [
                        311,
                        253
                    ],
                    [
                        786,
                        264
                    ],
                    [
                        765,
                        277
                    ],
                    [
                        124,
                        281
                    ],
                    [
                        144,
                        291
                    ],
                    [
                        282,
                        295
                    ],
                    [
                        1575,
                        310
                    ],
                    [
                        194,
                        333
                    ],
                    [
                        517,
                        427
                    ],
                    [
                        84,
                        449
                    ],
                    [
                        230,
                        456
                    ],
                    [
                        718,
                        463
                    ],
                    [
                        1010,
                        486
                    ],
                    [
                        91,
                        550
                    ],
                    [
                        1060,
                        688
                    ],
                    [
                        89,
                        779
                    ],
                    [
                        227,
                        792
                    ],
                    [
                        20,
                        841
                    ],
                    [
                        1846,
                        999
                    ],
                    [
                        300,
                        1074
                    ]
                ]
            }
        ]
    }
}